williamtoolbox/__init__.py
williamtoolbox/annotation.py
williamtoolbox/version.py
williamtoolbox/williamtoolbox_command.py
williamtoolbox/server/__init__.py
williamtoolbox/server/auth.py
williamtoolbox/server/auto_coder_chat_router.py
williamtoolbox/server/backend_server.py
williamtoolbox/server/byzer_sql_router.py
williamtoolbox/server/chat_router.py
williamtoolbox/server/config_router.py
williamtoolbox/server/file_router.py
williamtoolbox/server/model_router.py
williamtoolbox/server/openai_service_router.py
williamtoolbox/server/openapi_router.py
williamtoolbox/server/proxy_server.py
williamtoolbox/server/rag_router.py
williamtoolbox/server/request_types.py
williamtoolbox/server/search_router.py
williamtoolbox/server/super_analysis_router.py
williamtoolbox/server/user_manager.py
williamtoolbox/server/user_router.py
williamtoolbox/server/apps/__init__.py
williamtoolbox/server/apps/annotation_router.py
williamtoolbox/storage/__init__.py
williamtoolbox/storage/json_file.py
williamtoolbox/web/asset-manifest.json
williamtoolbox/web/favicon.ico
williamtoolbox/web/index.html
williamtoolbox/web/logo192.png
williamtoolbox/web/logo512.png
williamtoolbox/web/manifest.json
williamtoolbox/web/robots.txt
williamtoolbox/web/static/css/main.34c621e5.css
williamtoolbox/web/static/css/main.34c621e5.css.map
williamtoolbox/web/static/js/453.abd36b29.chunk.js
williamtoolbox/web/static/js/453.abd36b29.chunk.js.map
williamtoolbox/web/static/js/main.dc4f3d3d.js
williamtoolbox/web/static/js/main.dc4f3d3d.js.LICENSE.txt
williamtoolbox/web/static/js/main.dc4f3d3d.js.map
williamtoolbox-0.0.61.dist-info/METADATA
williamtoolbox-0.0.61.dist-info/WHEEL
williamtoolbox-0.0.61.dist-info/entry_points.txt
williamtoolbox-0.0.61.dist-info/top_level.txt
williamtoolbox-0.0.61.dist-info/RECORD
