Metadata-Version: 2.1
Name: williamtoolbox
Version: 0.0.61
Summary: williamtoolbox: William Toolbox
Author: allwefantasy
Classifier: Topic :: Scientific/Engineering :: Artificial Intelligence
Classifier: Programming Language :: Python :: 3.9
Classifier: Programming Language :: Python :: 3.10
Classifier: Programming Language :: Python :: 3.11
Requires-Dist: auto-coder
Requires-Dist: aiofiles
Requires-Dist: psutil
Requires-Dist: jproperties
Requires-Dist: sse-starlette
Requires-Dist: filelock
Requires-Dist: PyJWT
Requires-Dist: python-multipart
